{"nodes": [{"id": "execution_plan", "label": "ExecutionPlan", "file_type": "concept", "source_file": "docs/core/architecture.md", "source_location": null, "source_url": null, "captured_at": null, "author": null, "contributor": null}, {"id": "log_line", "label": "LogLine", "file_type": "concept", "source_file": "docs/core/architecture.md", "source_location": null, "source_url": null, "captured_at": null, "author": null, "contributor": null}, {"id": "unified_summary", "label": "Unified k6-style summary format", "file_type": "rationale", "source_file": "docs/core/architecture.md", "source_location": null, "source_url": null, "captured_at": null, "author": null, "contributor": null}, {"id": "design_no_proprietary", "label": "No proprietary integrations constraint", "file_type": "rationale", "source_file": "docs/core/architecture.md", "source_location": null, "source_url": null, "captured_at": null, "author": null, "contributor": null}, {"id": "design_external_subprocess", "label": "External engines as subprocesses constraint", "file_type": "rationale", "source_file": "docs/core/architecture.md", "source_location": null, "source_url": null, "captured_at": null, "author": null, "contributor": null}], "edges": [{"source": "perfscale_run", "target": "execution_plan", "relation": "references", "confidence": "EXTRACTED", "confidence_score": 1.0, "source_file": "docs/core/architecture.md", "source_location": null, "weight": 1.0}, {"source": "execution_plan", "target": "k6_runner", "relation": "references", "confidence": "EXTRACTED", "confidence_score": 1.0, "source_file": "docs/core/architecture.md", "source_location": null, "weight": 1.0}, {"source": "execution_plan", "target": "locust_runner", "relation": "references", "confidence": "EXTRACTED", "confidence_score": 1.0, "source_file": "docs/core/architecture.md", "source_location": null, "weight": 1.0}, {"source": "execution_plan", "target": "native_step_engine", "relation": "references", "confidence": "EXTRACTED", "confidence_score": 1.0, "source_file": "docs/core/architecture.md", "source_location": null, "weight": 1.0}, {"source": "k6_runner", "target": "log_line", "relation": "shares_data_with", "confidence": "EXTRACTED", "confidence_score": 1.0, "source_file": "docs/core/architecture.md", "source_location": null, "weight": 1.0}, {"source": "locust_runner", "target": "log_line", "relation": "shares_data_with", "confidence": "EXTRACTED", "confidence_score": 1.0, "source_file": "docs/core/architecture.md", "source_location": null, "weight": 1.0}, {"source": "native_step_engine", "target": "log_line", "relation": "shares_data_with", "confidence": "EXTRACTED", "confidence_score": 1.0, "source_file": "docs/core/architecture.md", "source_location": null, "weight": 1.0}, {"source": "k6_runner", "target": "unified_summary", "relation": "implements", "confidence": "EXTRACTED", "confidence_score": 1.0, "source_file": "docs/core/architecture.md", "source_location": null, "weight": 1.0}, {"source": "locust_runner", "target": "unified_summary", "relation": "implements", "confidence": "EXTRACTED", "confidence_score": 1.0, "source_file": "docs/core/architecture.md", "source_location": null, "weight": 1.0}, {"source": "native_step_engine", "target": "unified_summary", "relation": "implements", "confidence": "EXTRACTED", "confidence_score": 1.0, "source_file": "docs/core/architecture.md", "source_location": null, "weight": 1.0}, {"source": "perfscale_core", "target": "log_line", "relation": "references", "confidence": "EXTRACTED", "confidence_score": 1.0, "source_file": "docs/core/architecture.md", "source_location": null, "weight": 1.0}, {"source": "perfscale_core", "target": "execution_plan", "relation": "references", "confidence": "EXTRACTED", "confidence_score": 1.0, "source_file": "docs/core/architecture.md", "source_location": null, "weight": 1.0}, {"source": "native_step_engine", "target": "design_external_subprocess", "relation": "references", "confidence": "INFERRED", "confidence_score": 0.75, "source_file": "docs/core/architecture.md", "source_location": null, "weight": 1.0}], "hyperedges": [{"id": "three_engines_one_interface", "label": "Three engines, one LogLine interface", "nodes": ["k6_runner", "locust_runner", "native_step_engine", "log_line", "unified_summary"], "relation": "participate_in", "confidence": "EXTRACTED", "confidence_score": 1.0, "source_file": "docs/core/architecture.md"}]}